chainclient.py
chainclient-0.5.0.dist-info/WHEEL
chainclient-0.5.0.dist-info/RECORD
chainclient-0.5.0.dist-info/top_level.txt
chainclient-0.5.0.dist-info/DESCRIPTION.rst
chainclient-0.5.0.dist-info/metadata.json
chainclient-0.5.0.dist-info/METADATA
