Metadata-Version: 2.0
Name: chainclient
Version: 0.5.0
Summary: A Python client for the Chain API
Home-page: http://github.com/ssfrr/chainclient.py
Author: Spencer Russell
Author-email: sfr@media.mit.edu
License: MIT
Platform: UNKNOWN
Requires-Dist: requests
